[
  {
    "id": "e60f58b4-d1e8-450d-8532-0d364ec4ce9c",
    "data": [
      {
        "text": "always a pleasure to see you",
        "userDefined": false
      }
    ],
    "isTemplate": false,
    "count": 0,
    "updated": 0
  },
  {
    "id": "cef49f5e-c03e-4db6-8f7c-3ed4914734c7",
    "data": [
      {
        "text": "lovely",
        "meta": "@sys.ignore",
        "userDefined": false
      },
      {
        "text": " to see you",
        "userDefined": false
      }
    ],
    "isTemplate": false,
    "count": 0,
    "updated": 0
  },
  {
    "id": "034df9b8-2ab0-4a07-824d-aacffcce57a8",
    "data": [
      {
        "text": "I\u0027m glad to see you",
        "userDefined": false
      }
    ],
    "isTemplate": false,
    "count": 0,
    "updated": 0
  },
  {
    "id": "0de06b74-70b4-4c3a-a78f-7acf961236bf",
    "data": [
      {
        "text": "it\u0027s",
        "meta": "@sys.ignore",
        "userDefined": false
      },
      {
        "text": " ",
        "userDefined": false
      },
      {
        "text": "good",
        "meta": "@sys.ignore",
        "userDefined": false
      },
      {
        "text": " to see you too",
        "userDefined": false
      }
    ],
    "isTemplate": false,
    "count": 1,
    "updated": 0
  },
  {
    "id": "dc22771f-6699-44cb-b036-d55038fe027c",
    "data": [
      {
        "text": "it\u0027s",
        "meta": "@sys.ignore",
        "userDefined": false
      },
      {
        "text": " ",
        "userDefined": false
      },
      {
        "text": "nice",
        "meta": "@sys.ignore",
        "userDefined": false
      },
      {
        "text": " to see you",
        "userDefined": false
      }
    ],
    "isTemplate": false,
    "count": 1,
    "updated": 0
  },
  {
    "id": "5cd995a1-4793-4510-9160-2cd55a4073ac",
    "data": [
      {
        "text": "nice",
        "meta": "@sys.ignore",
        "userDefined": false
      },
      {
        "text": " to see you",
        "userDefined": false
      }
    ],
    "isTemplate": false,
    "count": 0,
    "updated": 0
  },
  {
    "id": "e99c6502-9afe-4100-9c4e-d7f175f54373",
    "data": [
      {
        "text": "good",
        "meta": "@sys.ignore",
        "userDefined": false
      },
      {
        "text": " to see you",
        "userDefined": false
      }
    ],
    "isTemplate": false,
    "count": 1,
    "updated": 0
  },
  {
    "id": "efd2a3db-4d6b-4d23-a7ad-35a705b9c8f1",
    "data": [
      {
        "text": "good",
        "meta": "@sys.ignore",
        "userDefined": false
      },
      {
        "text": " to see you again",
        "userDefined": false
      }
    ],
    "isTemplate": false,
    "count": 2,
    "updated": 0
  },
  {
    "id": "af07c3ae-a643-4fa0-b05a-8bdcdd1d999d",
    "data": [
      {
        "text": "nice",
        "meta": "@sys.ignore",
        "userDefined": false
      },
      {
        "text": " to see you again",
        "userDefined": false
      }
    ],
    "isTemplate": false,
    "count": 1,
    "updated": 0
  },
  {
    "id": "cd34e014-1c7c-4922-b6d1-6d375b435ed4",
    "data": [
      {
        "text": "it\u0027s",
        "meta": "@sys.ignore",
        "userDefined": false
      },
      {
        "text": " ",
        "userDefined": false
      },
      {
        "text": "good",
        "meta": "@sys.ignore",
        "userDefined": false
      },
      {
        "text": " to see you",
        "userDefined": false
      }
    ],
    "isTemplate": false,
    "count": 0,
    "updated": 0
  },
  {
    "id": "f274c15d-907b-496c-98d6-98a904328c7b",
    "data": [
      {
        "text": "great to see you again",
        "userDefined": false
      }
    ],
    "isTemplate": false,
    "count": 0,
    "updated": 0
  },
  {
    "id": "322c6fa0-1aed-4aab-8590-dea70771d5f9",
    "data": [
      {
        "text": "glad to see you",
        "userDefined": false
      }
    ],
    "isTemplate": false,
    "count": 0,
    "updated": 0
  },
  {
    "id": "3dea782e-4e47-42be-8d49-1243a2bd2877",
    "data": [
      {
        "text": "I am glad to see you again",
        "userDefined": false
      }
    ],
    "isTemplate": false,
    "count": 0,
    "updated": 0
  },
  {
    "id": "91c32dd7-cd59-41a1-9bff-28db713744cb",
    "data": [
      {
        "text": "glad to see you too",
        "userDefined": false
      }
    ],
    "isTemplate": false,
    "count": 1,
    "updated": 0
  },
  {
    "id": "858d1ec5-b86c-47f8-b24b-240d6aff1416",
    "data": [
      {
        "text": "great to see you too",
        "userDefined": false
      }
    ],
    "isTemplate": false,
    "count": 0,
    "updated": 0
  },
  {
    "id": "2d6adffd-96a6-4a86-9a34-fb037d9c6386",
    "data": [
      {
        "text": "how ",
        "userDefined": false
      },
      {
        "text": "good",
        "meta": "@sys.ignore",
        "userDefined": false
      },
      {
        "text": " ",
        "userDefined": false
      },
      {
        "text": "it",
        "meta": "@sys.ignore",
        "userDefined": false
      },
      {
        "text": " is to see you",
        "userDefined": false
      }
    ],
    "isTemplate": false,
    "count": 1,
    "updated": 0
  },
  {
    "id": "3b2ef0f2-8f7e-472b-b571-a929f5e14de0",
    "data": [
      {
        "text": "great to see you",
        "userDefined": false
      }
    ],
    "isTemplate": false,
    "count": 1,
    "updated": 0
  }
]